LICENSE
README.rst
setup.py
columnflow/__init__.py
columnflow/__version__.py
columnflow/columnar_util.py
columnflow/util.py
columnflow/calibration/__init__.py
columnflow/calibration/example.py
columnflow/calibration/jets.py
columnflow/calibration/met.py
columnflow/example_config/__init__.py
columnflow/example_config/analysis_st.py
columnflow/example_config/campaign_2018.py
columnflow/inference/__init__.py
columnflow/inference/datacard.py
columnflow/inference/example.py
columnflow/ml/__init__.py
columnflow/ml/example.py
columnflow/plotting/__init__.py
columnflow/plotting/example.py
columnflow/plotting/plot2d.py
columnflow/plotting/plot_util.py
columnflow/production/__init__.py
columnflow/production/btag.py
columnflow/production/categories.py
columnflow/production/electron.py
columnflow/production/example.py
columnflow/production/gen_top_decay.py
columnflow/production/mc_weight.py
columnflow/production/muon.py
columnflow/production/normalization.py
columnflow/production/pileup.py
columnflow/production/processes.py
columnflow/production/seeds.py
columnflow/production/util.py
columnflow/selection/__init__.py
columnflow/selection/example.py
columnflow/selection/matching.py
columnflow/tasks/__init__.py
columnflow/tasks/calibration.py
columnflow/tasks/cutflow.py
columnflow/tasks/external.py
columnflow/tasks/histograms.py
columnflow/tasks/inference.py
columnflow/tasks/ml.py
columnflow/tasks/plotting.py
columnflow/tasks/production.py
columnflow/tasks/reduction.py
columnflow/tasks/selection.py
columnflow/tasks/framework/__init__.py
columnflow/tasks/framework/base.py
columnflow/tasks/framework/mixins.py
columnflow/tasks/framework/plotting.py
columnflow/tasks/framework/remote.py
flow.egg-info/PKG-INFO
flow.egg-info/SOURCES.txt
flow.egg-info/dependency_links.txt
flow.egg-info/not-zip-safe
flow.egg-info/requires.txt
flow.egg-info/top_level.txt