Metadata-Version: 2.1
Name: flow
Version: 0.1.2
Summary: columnflow
Home-page: https://github.com/uhh-cms/columnflow
Author: Marcel Rieger
Author-email: todo@uni-hamburg.de
License: BSD-3-Clause
Keywords: physics,analysis,experiment,columnar,vectoized,law,order,luigi,lhc,cms
Platform: UNKNOWN
Classifier: Programming Language :: Python
Classifier: Programming Language :: Python :: 3
Classifier: Programming Language :: Python :: 3.7
Classifier: Programming Language :: Python :: 3.8
Classifier: Programming Language :: Python :: 3.9
Classifier: Programming Language :: Python :: 3.10
Classifier: Development Status :: 4 - Beta
Classifier: Operating System :: OS Independent
Classifier: License :: OSI Approved :: BSD License
Classifier: Intended Audience :: Developers
Classifier: Intended Audience :: Science/Research
Classifier: Intended Audience :: Information Technology
Requires-Python: >=3.7, <4
License-File: LICENSE
